{"saveName":"Mundo Inicial","timestamp":"2026-05-26T16:14:46.193898","currentAreaId":4,"elapsedMinutes":6,"minutesSincePopulate":6,"log":["Apoiou Ana = true","Dialogo concluido: Ecrã Partido","Movimento: Sala de Aula (+3 min).","Dialogo (auto): Frente a Frente","Confrontou Tiago = true","Dialogo concluido: Frente a Frente","Dialogo ativado: Não Estás Sozinha.","Apoiou Ana = true","Confrontou Tiago = true","Dialogo ativado: Não Estás Sozinha.","Dialogo concluido: Ecrã Partido","Movimento: Pátio."],"gameFlags":{"1":true,"2":true,"3":false,"4":false,"5":false},"characterPositions":{"1":1,"2":2,"3":3,"0":0}}